pySRTM/DEM.py
pySRTM/DataAccess.py
pySRTM/__init__.py
pySRTM-0.0.3.dist-info/LICENSE
pySRTM-0.0.3.dist-info/METADATA
pySRTM-0.0.3.dist-info/WHEEL
pySRTM-0.0.3.dist-info/top_level.txt
pySRTM-0.0.3.dist-info/RECORD
